weilan/__init__.py
weilan/_version.py
weilan/tests/__init__.py
weilan/tests/conftest.py
weilan/tests/test_examples.py
weilan-0.0.1.dist-info/AUTHORS.rst
weilan-0.0.1.dist-info/LICENSE
weilan-0.0.1.dist-info/METADATA
weilan-0.0.1.dist-info/WHEEL
weilan-0.0.1.dist-info/entry_points.txt
weilan-0.0.1.dist-info/top_level.txt
weilan-0.0.1.dist-info/RECORD
