Metadata-Version: 2.1
Name: weilan
Version: 0.0.1
Summary: A weilan future.
Home-page: https://github.com/appletree120th/weilan
Author: Apple Tree
Author-email: appletree120th@gmail.com
License: BSD (3-clause)
Platform: UNKNOWN
Classifier: Development Status :: 2 - Pre-Alpha
Classifier: Natural Language :: English
Classifier: Programming Language :: Python :: 3
Requires-Python: >=3.8
